reachgenie-0.1.0.dist-info/licenses/LICENSE
src/__init__.py
src/auth.py
src/bland_client.py
src/config.py
src/database.py
src/main.py
src/models.py
src/perplexity_enrichment.py
src/celery_app/__init__.py
src/celery_app/config.py
src/celery_app/tasks/__init__.py
src/celery_app/tasks/process_do_not_contact.py
src/celery_app/tasks/process_leads.py
src/celery_app/tasks/run_campaign.py
src/prompts/company_info_prompt.py
src/prompts/company_insights_prompt.py
src/templates/email_templates.py
src/web/bland_agent_widget.html
src/web/bland_agent_widget_proxy.html
reachgenie-0.1.0.dist-info/METADATA
reachgenie-0.1.0.dist-info/WHEEL
reachgenie-0.1.0.dist-info/entry_points.txt
reachgenie-0.1.0.dist-info/top_level.txt
reachgenie-0.1.0.dist-info/RECORD
