Metadata-Version: 2.4
Name: reachgenie
Version: 0.1.0
Summary: AI-powered multi-channel sales automation platform
Home-page: https://github.com/alinaqi/reachgenie
Author: Ali Shaheen
Author-email: Ali Shaheen <ashaheen@workhub.ai>
License-Expression: AGPL-3.0-only
Project-URL: Homepage, https://github.com/alinaqi/reachgenie
Project-URL: Documentation, https://github.com/alinaqi/reachgenie#readme
Project-URL: Repository, https://github.com/alinaqi/reachgenie
Project-URL: Bug Tracker, https://github.com/alinaqi/reachgenie/issues
Keywords: ai,sales,automation,email,phone,linkedin,sdr,outbound,campaigns
Classifier: Development Status :: 4 - Beta
Classifier: Intended Audience :: Developers
Classifier: Operating System :: OS Independent
Classifier: Programming Language :: Python :: 3
Classifier: Programming Language :: Python :: 3.12
Classifier: Framework :: FastAPI
Classifier: Topic :: Communications :: Email
Classifier: Topic :: Office/Business :: Scheduling
Classifier: Topic :: Software Development :: Libraries :: Python Modules
Requires-Python: >=3.12
License-File: LICENSE
Provides-Extra: dev
Requires-Dist: pytest>=7.0.0; extra == "dev"
Requires-Dist: pytest-asyncio>=0.21.0; extra == "dev"
Requires-Dist: pytest-cov>=4.0.0; extra == "dev"
Requires-Dist: black>=23.0.0; extra == "dev"
Requires-Dist: flake8>=6.0.0; extra == "dev"
Requires-Dist: mypy>=1.0.0; extra == "dev"
Dynamic: author
Dynamic: home-page
Dynamic: license-file
Dynamic: requires-python
